CHANGES.rst
MANIFEST.in
README.rst
setup.py
atilla/__init__.py
atilla/cache.py
atilla/clients.py
atilla/commands.py
atilla/exception_handlers.py
atilla/exceptions.py
atilla/links.py
atilla/pagination.py
atilla/response.py
atilla/serialization.py
atilla/server.py
atilla/transaction.py
atilla/validators.py
atilla/wrappers.py
atilla.egg-info/PKG-INFO
atilla.egg-info/SOURCES.txt
atilla.egg-info/dependency_links.txt
atilla.egg-info/requires.txt
atilla.egg-info/top_level.txt
atilla/ext/__init__.py
atilla/ext/halogen/__init__.py
atilla/ext/halogen/types.py
atilla/formatting/__init__.py
atilla/formatting/i18n.py
tests/__init__.py
tests/conftest.py
tests/settings.py
tests/test_cache.py
tests/test_exceptions.py
tests/test_halogen.py
tests/test_links.py
tests/test_pagination.py
tests/test_response.py
tests/test_server.py
tests/test_validators.py